tootstream/__init__.py
tootstream/config.py
tootstream/toot.py
tootstream/toot_parser.py
tootstream-0.3.7.dist-info/METADATA
tootstream-0.3.7.dist-info/RECORD
tootstream-0.3.7.dist-info/WHEEL
tootstream-0.3.7.dist-info/entry_points.txt
tootstream-0.3.7.dist-info/top_level.txt
