Metadata-Version: 2.1
Name: tootstream
Version: 0.3.7
Summary: A command line interface for interacting with Mastodon instances
Home-page: http://www.github.com/magicalraccoon/tootstream
Author: Sara Murray
Author-email: saramurray@protonmail.com
License: MIT
Keywords: mastodon,mastodon.social,toot,tootstream
Platform: UNKNOWN
Requires-Python: >=3
Requires-Dist: click (>=6.7)
Requires-Dist: Mastodon.py (==1.4.5)
Requires-Dist: colored (>=1.3.93)
Requires-Dist: humanize (>=0.5.1)
Requires-Dist: emoji (>=0.4.5)
